appleauth/__init__.py
appleauth/appleauth.py
scrapy_appleauth-0.1.2.dist-info/METADATA
scrapy_appleauth-0.1.2.dist-info/WHEEL
scrapy_appleauth-0.1.2.dist-info/top_level.txt
scrapy_appleauth-0.1.2.dist-info/RECORD
