Metadata-Version: 2.1
Name: scrapy-appleauth
Version: 0.1.2
Summary: apple auth downloader middleware for scrapy
Home-page: https://github.com/geek-dc/scrapy-appleauth
Author: derekchan
Author-email: dchan0831@gmail.com
License: MIT Licence
Keywords: pip,datacanvas,eds,xiaoh
Platform: any
Requires-Dist: pyjwt
